opengig_openai_wrapper/__init__.py
opengig_openai_wrapper-0.1.1.dist-info/METADATA
opengig_openai_wrapper-0.1.1.dist-info/WHEEL
opengig_openai_wrapper-0.1.1.dist-info/RECORD
