Metadata-Version: 2.1
Name: opengig_openai_wrapper
Version: 0.1.1
Summary: easy to use openai apis
Author: Abhilasha
Author-email: singhabhilasha4042@gmail.com
Requires-Python: >=3.10,<4.0
Classifier: Programming Language :: Python :: 3
Classifier: Programming Language :: Python :: 3.10
Classifier: Programming Language :: Python :: 3.11
Classifier: Programming Language :: Python :: 3.12
Classifier: Programming Language :: Python :: 3.13
Requires-Dist: openai (>=1.57.4,<2.0.0)
Requires-Dist: python-dotenv (>=1.0.1,<2.0.0)
